{
  "values": [
    {
      "id": "ff0fd1af-b5f4-4639-befb-9b93f0064ec4",
      "idea": "this is my idea number 1",
      "email": "a@gmail.com"
    },
    {
      "id": "a8879bc8-70e7-48c2-b0cd-b649ca1c2a0f",
      "idea": "abcd idea",
      "email": "a@gmail.com"
    },
    {
      "id": "0ac0d550-f143-4da4-ab0d-b78d5093fddd",
      "idea": "I have an idea to make a new type of mobile cover that protects your data from identity theft.",
      "email": "45@567.com"
    },
    {
      "id": "16867783-fbc2-4077-842b-bae0b2d5b01f",
      "idea": "test idea ",
      "email": "server@gmail.com"
    },
    {
      "id": "1de7ef0c-f481-4f2a-a1d1-d224015615dd",
      "idea": "offline idea",
      "email": "test@34.com"
    },
    {
      "id": "08c0f90d-492d-4276-9fdd-30a8917ba80a",
      "idea": "Testing ",
      "email": "tes@gmail.com"
    }
  ]
}